setup.py
pytddmon.egg-info/PKG-INFO
pytddmon.egg-info/SOURCES.txt
pytddmon.egg-info/dependency_links.txt
pytddmon.egg-info/top_level.txt
pytddmon.egg-info/zip-safe
src/pytddmon.py