Metadata-Version: 1.0
Name: pytddmon
Version: 1.0.1
Summary: continuous unit testing in Python
Home-page: https://github.com/objarni/pytddmon
Author: Olof Bjarnason, Fredrik Wendt, Krunoslav Saho,
Author-email: olof.bjarnason@gmail.com
License: MIT
Platform: UNKNOWN
